muninn_cams.py
muninn_cams-2.1.dist-info/LICENSE
muninn_cams-2.1.dist-info/METADATA
muninn_cams-2.1.dist-info/WHEEL
muninn_cams-2.1.dist-info/top_level.txt
muninn_cams-2.1.dist-info/RECORD
